aiforge/__init__.py
aiforge/adapters/__init__.py
aiforge/adapters/input/__init__.py
aiforge/adapters/input/cli_input_adapter.py
aiforge/adapters/input/gui_input_adapter.py
aiforge/adapters/input/input_adapter.py
aiforge/adapters/input/input_adapter_manager.py
aiforge/adapters/input/input_processors.py
aiforge/adapters/input/mobile_input_adapter.py
aiforge/adapters/input/voice_input_adapter.py
aiforge/adapters/input/web_input_adapter.py
aiforge/adapters/output/__init__.py
aiforge/adapters/output/ai_ui_adapter.py
aiforge/adapters/output/enhanced_hybrid_adapter.py
aiforge/adapters/output/learning_Interface.py
aiforge/adapters/output/rule_based_adapter.py
aiforge/adapters/output/task_type_detector.py
aiforge/adapters/output/ui_type_recommender.py
aiforge/cache/__init__.py
aiforge/cache/action_matcher.py
aiforge/cache/code_cache.py
aiforge/cache/dynamic_task_type_manager.py
aiforge/cache/semantic_cache.py
aiforge/cli/__init__.py
aiforge/cli/cli.py
aiforge/cli/main.py
aiforge/cli/wizard.py
aiforge/cli/commands/manager.py
aiforge/config/__init__.py
aiforge/config/config.py
aiforge/config/config_sync.py
aiforge/config/default.toml
aiforge/config/extension_config.py
aiforge/config/extensions.toml
aiforge/config/remote_config.py
aiforge/core/__init__.py
aiforge/core/engine.py
aiforge/core/orchestrator.py
aiforge/core/path_manager.py
aiforge/core/prompt.py
aiforge/core/result.py
aiforge/core/runner.py
aiforge/core/task_types.py
aiforge/core/helpers/__init__.py
aiforge/core/helpers/cache_helper.py
aiforge/core/managers/__init__.py
aiforge/core/managers/config_manager.py
aiforge/core/managers/content_generation_manager.py
aiforge/core/managers/execution_manager.py
aiforge/core/managers/search_manager.py
aiforge/core/managers/shutdown_manager.py
aiforge/core/managers/streaming_execution_manager.py
aiforge/core/task/__init__.py
aiforge/core/task/executor.py
aiforge/core/task/feedback_optimizer.py
aiforge/core/task/manager.py
aiforge/core/task/task.py
aiforge_engine-0.0.19.dist-info/METADATA
aiforge_engine-0.0.19.dist-info/WHEEL
aiforge_engine-0.0.19.dist-info/entry_points.txt
aiforge_engine-0.0.19.dist-info/licenses/LICENSE
aiforge_engine-0.0.19.dist-info/RECORD
