Metadata-Version: 2.4
Name: aiforge-engine
Version: 0.0.19
Summary: Intelligent Intent Adaptive Execution Engine - 智能意图自适应执行引擎
Project-URL: Homepage, https://github.com/iniwap/AIForge
Project-URL: Documentation, https://iniwap.github.io/AIForge
Project-URL: Repository, https://github.com/iniwap/AIForge
Project-URL: Bug Tracker, https://github.com/iniwap/AIForge/issues
Project-URL: Changelog, https://github.com/iniwap/AIForge/releases
Project-URL: Source Code, https://github.com/iniwap/AIForge
Project-URL: Discord, https://discord.gg/Vp35uSBsrw
Project-URL: Twitter, https://twitter.com/iafun_tipixel
Author-email: iniwap <iniwaper@gmail.com>
Maintainer-email: iniwap <iniwaper@gmail.com>
License: Apache 2.0
License-File: LICENSE
Keywords: agent,agent-zero,ai,ai-agents,ai-tools,aipyapp,automation,code-generation,crewai,engine,execution,intent,llm,manus,natural-language
Classifier: Development Status :: 3 - Alpha
Classifier: Environment :: Console
Classifier: Environment :: Web Environment
Classifier: Intended Audience :: Developers
Classifier: License :: OSI Approved :: Apache Software License
Classifier: Operating System :: OS Independent
Classifier: Programming Language :: Python :: 3
Classifier: Programming Language :: Python :: 3.10
Classifier: Programming Language :: Python :: 3.11
Classifier: Programming Language :: Python :: 3.12
Classifier: Topic :: Internet :: WWW/HTTP :: Dynamic Content
Classifier: Topic :: Scientific/Engineering :: Artificial Intelligence
Classifier: Topic :: Software Development :: Code Generators
Classifier: Topic :: Software Development :: Libraries :: Python Modules
Requires-Python: >=3.10
Requires-Dist: beautifulsoup4>=4.9.0
Requires-Dist: click>=8.0.0
Requires-Dist: peewee>=3.14.0
Requires-Dist: pydantic>=2.0.0
Requires-Dist: python-dateutil>=2.8.0
Requires-Dist: requests>=2.25.0
Requires-Dist: rich>=12.0.0
Requires-Dist: setuptools
Requires-Dist: tomlkit>=0.10.0
Requires-Dist: typing-extensions>=4.0.0
Provides-Extra: all
Requires-Dist: docker>=6.0.0; extra == 'all'
Requires-Dist: fastapi>=0.100.0; extra == 'all'
Requires-Dist: jinja2>=3.1.0; extra == 'all'
Requires-Dist: psutil>=5.8.0; extra == 'all'
Requires-Dist: pywebview>=4.0.0; extra == 'all'
Requires-Dist: pyyaml>=6.0.0; extra == 'all'
Requires-Dist: sentence-transformers>=2.0.0; extra == 'all'
Requires-Dist: uvicorn>=0.20.0; extra == 'all'
Provides-Extra: deploy
Requires-Dist: docker>=6.0.0; extra == 'deploy'
Requires-Dist: pyyaml>=6.0.0; extra == 'deploy'
Provides-Extra: dev
Requires-Dist: pytest>=7.0.0; extra == 'dev'
Requires-Dist: python-dotenv>=1.0.0; extra == 'dev'
Provides-Extra: gui
Requires-Dist: pillow>=8.0.0; extra == 'gui'
Requires-Dist: pystray>=0.19.0; extra == 'gui'
Requires-Dist: pywebview>=4.0.0; extra == 'gui'
Requires-Dist: pywin32>=306; (platform_system == 'Windows') and extra == 'gui'
Provides-Extra: transformers
Requires-Dist: sentence-transformers>=2.0.0; extra == 'transformers'
Provides-Extra: web
Requires-Dist: fastapi>=0.100.0; extra == 'web'
Requires-Dist: jinja2>=3.1.0; extra == 'web'
Requires-Dist: psutil>=5.8.0; extra == 'web'
Requires-Dist: uvicorn>=0.20.0; extra == 'web'
